{
  "runTests": true,
  "runScopes": [
    {
      "name": "all",
      "run": true
    }
  ],
  "logging": {
    "on" : true,
    "filename" : "stdout",
    "logs" : {}
  },
  "additionalPlugins": {
    "DummyTestLibOne" : "../tests/dummyTestLibOne/libdummyTestLibOne.so"
  },
  "outputEngine": {
    "type": "debug",
    "config": {
    }
  },
  "injectionPoints": [
      {
        "name" : "initialization",
        "package" : "VNV",
        "tests" : [
            {
                "name" : "provenance",
                "package" : "VNV",
                "runScope" : ["all"],
                "config" : {
                    "expectedResult" : {},
                    "configuration": {
                    },
                    "parameters": {
                        "argc" : "argc",
                        "argv" : "argv",
                        "config" : "config"
                    }
                }
            }
        ]
      }
  ]
}
